xontrib/back2dir.py
xontrib_back2dir-0.1.3.dist-info/LICENSE
xontrib_back2dir-0.1.3.dist-info/METADATA
xontrib_back2dir-0.1.3.dist-info/WHEEL
xontrib_back2dir-0.1.3.dist-info/top_level.txt
xontrib_back2dir-0.1.3.dist-info/RECORD
