Metadata-Version: 2.1
Name: xontrib-back2dir
Version: 0.1.3
Summary: Return to the most recently used directory when starting the xonsh shell.
Home-page: https://github.com/anki-code/xontrib-back2dir
Author: anki-code
Author-email: anki-code@no.no
License: MIT
Project-URL: Documentation, https://github.com/anki-code/xontrib-back2dir/blob/master/README.md
Project-URL: Code, https://github.com/anki-code/xontrib-back2dir
Project-URL: Issue tracker, https://github.com/anki-code/xontrib-back2dir/issues
Platform: any
Classifier: Programming Language :: Python :: 3
Classifier: Programming Language :: Python :: 3.6
Classifier: Programming Language :: Python :: 3.7
Classifier: Programming Language :: Python :: 3.8
Classifier: License :: OSI Approved :: MIT License
Classifier: Operating System :: OS Independent
Classifier: Topic :: System :: Shells
Classifier: Topic :: System :: System Shells
Classifier: Topic :: Terminals
Requires-Python: >=3.6
License-File: LICENSE
